scalepy/__init__.py
scalepy/scale.py
scalepy-1.0.dist-info/DESCRIPTION.rst
scalepy-1.0.dist-info/METADATA
scalepy-1.0.dist-info/RECORD
scalepy-1.0.dist-info/WHEEL
scalepy-1.0.dist-info/entry_points.txt
scalepy-1.0.dist-info/metadata.json
scalepy-1.0.dist-info/top_level.txt
