Metadata-Version: 2.0
Name: scalepy
Version: 1.0
Summary: Provies renaming utility for Nikon output files.
Home-page: https://github.com/ChrisoftheBoyerClan/scale.py
Author: Christopher Boyer
Author-email: ChrisoftheBoyerClan@gmail.com
License: MIT
Keywords: scale image resize
Platform: UNKNOWN
